zhangUtils/__init__.py
zhangUtils/train.py
zhangUtils/util.py
zhangUtils-0.2.2.dist-info/METADATA
zhangUtils-0.2.2.dist-info/WHEEL
zhangUtils-0.2.2.dist-info/top_level.txt
zhangUtils-0.2.2.dist-info/RECORD
